LICENSE
MANIFEST.in
README.md
requirements.txt
setup.cfg
setup.py
versioneer.py
veros_extra_setups/__init__.py
veros_extra_setups/_version.py
veros_extra_setups.egg-info/PKG-INFO
veros_extra_setups.egg-info/SOURCES.txt
veros_extra_setups.egg-info/dependency_links.txt
veros_extra_setups.egg-info/entry_points.txt
veros_extra_setups.egg-info/not-zip-safe
veros_extra_setups.egg-info/requires.txt
veros_extra_setups.egg-info/top_level.txt
veros_extra_setups/setups/__init__.py
veros_extra_setups/setups/acc_sector/__init__.py
veros_extra_setups/setups/acc_sector/acc_sector.py
veros_extra_setups/setups/fjord/__init__.py
veros_extra_setups/setups/fjord/fjord.py
veros_extra_setups/setups/wave_propagation/__init__.py
veros_extra_setups/setups/wave_propagation/assets.json
veros_extra_setups/setups/wave_propagation/na_mask.png
veros_extra_setups/setups/wave_propagation/topography_idealized.png
veros_extra_setups/setups/wave_propagation/wave_propagation.py